{
  "catalog": [
    {
      "chars": 151,
      "derived_from": [],
      "id": "EdVG5qNm2rY",
      "kind": "metadata",
      "method": "yt-dlp",
      "ref": "EdVG5qNm2rY",
      "sha256": "1a0979ac83189638f692c6be99a15a204f4ca8c6afa272ec368de5a057266846",
      "source": "video",
      "title": "21 Yr Old Disproves 4 Decades Old Belief in Computing"
    },
    {
      "chars": 16009,
      "derived_from": [],
      "id": "EdVG5qNm2rY",
      "kind": "transcript",
      "method": "yt-dlp",
      "ref": "EdVG5qNm2rY",
      "sha256": "304feec6cab459937db1d38aa87abcbda3979a176799cbf6c3724e55a2fb29cf",
      "source": "video",
      "title": "21 Yr Old Disproves 4 Decades Old Belief in Computing"
    }
  ],
  "digest": {
    "receipts": [
      {
        "derived_from": [],
        "id": "EdVG5qNm2rY",
        "kind": "metadata",
        "method": "yt-dlp",
        "ref": "EdVG5qNm2rY",
        "sha256": "1a0979ac83189638f692c6be99a15a204f4ca8c6afa272ec368de5a057266846",
        "source": "video",
        "title": "21 Yr Old Disproves 4 Decades Old Belief in Computing"
      },
      {
        "derived_from": [],
        "id": "EdVG5qNm2rY",
        "kind": "transcript",
        "method": "yt-dlp",
        "ref": "EdVG5qNm2rY",
        "sha256": "304feec6cab459937db1d38aa87abcbda3979a176799cbf6c3724e55a2fb29cf",
        "source": "video",
        "title": "21 Yr Old Disproves 4 Decades Old Belief in Computing"
      }
    ],
    "seal": "1798c8b44d88ad7ea25140a2db5ff239a33892f5eec6b9d2dfc85689960d0370"
  },
  "dropped": 0,
  "schema": "gather.catalog-digest/v1",
  "stored": {
    "added": 2,
    "deduped": 0,
    "total": 2
  },
  "verified": true
}
