{
  "claims": [
    {
      "falsification": "Claim 1 differs from pass 0101 artifacts or receipts are missing",
      "text": "Pass 0101 created an InequalitySafeBQMReceipt/v1 artifact with status INEQUALITY_SAFE_BQM_RECEIPT_MATCH, sha256 c48b4fd7e6ef88dddfbb0f8a895bcdc97b91443c31de9641072784fba324f5c2, and seal cd3fc1e66878fb9529f8e0c61890830819fcc3456dce0a96a24dcbfdf7eb4b1a."
    },
    {
      "falsification": "Claim 2 differs from pass 0101 artifacts or receipts are missing",
      "text": "Pass 0101 binds Ocean/dimod pass 0100 and uses dimod version 0.12.22."
    },
    {
      "falsification": "Claim 3 differs from pass 0101 artifacts or receipts are missing",
      "text": "Pass 0101 counterexample has true feasible optimum value 10 and weight 3."
    },
    {
      "falsification": "Claim 4 differs from pass 0101 artifacts or receipts are missing",
      "text": "Pass 0101 equality penalty selects value 19 with feasible=False."
    },
    {
      "falsification": "Claim 5 differs from pass 0101 artifacts or receipts are missing",
      "text": "Pass 0101 slack-variable penalty selects value 10 with feasible=True."
    },
    {
      "falsification": "Claim 6 differs from pass 0101 artifacts or receipts are missing",
      "text": "Pass 0101 records law candidate knapsack_inequality_bqm_requires_slack_or_inequality_encoding with status LAW_CANDIDATE."
    },
    {
      "falsification": "Claim 7 differs from pass 0101 artifacts or receipts are missing",
      "text": "Pass 0101 flagship receipts for Forum, Index, and Telos all have MATCH status."
    },
    {
      "falsification": "Claim 8 differs from pass 0101 artifacts or receipts are missing",
      "text": "Pass 0101 records unsupported_claim_count 0 and current_promoted_natural_laws length 0."
    },
    {
      "falsification": "Claim 9 differs from pass 0101 artifacts or receipts are missing",
      "text": "Pass 0101 composer sha256 is 16725ad76bcfb9cd3a6455c84583b88603a3ef2346ae1ffc5fdb2eafd1b6535b, packet sha256 is 1f5f3a08120f9eea2f2ea7f157f5ea41b104963b6dacf002c380c70804c346a3, brief sha256 is b631d91056eaf3e4de5fc9f270e1d55be69a2977dab4e01f0b6715ddd4ece4d8, steelman sha256 is 5d046bf05784fb1023497cdc42a635052412cd41a63bc39d7d5cc4270b2470fc, test sha256 is 8bf2bfcf152e6bf4d476361046601384365ec5b870919ce5e27b32d76ad96223, and tool_receipts sha256 is c1c1f2691e812d175eba21271d94ea99f4129aed29de5850c2e0e34d7a33c045 with test_receipt status MATCH."
    }
  ],
  "disposition": "fenced",
  "title": "Dogfood Pass 0101 Inequality-Safe BQM"
}
