{
  "claims": [
    {
      "falsification": "Claim 1 differs from artifact values or receipts are missing",
      "text": "Pass 0146 created an AdapterRetryPolicyReceipt/v1 artifact with status ADAPTER_RETRY_POLICY_MATCH and seal 8a20aae5a90e77621ecb7498d90665b17e53393b33109768e92eab17feaea4a5."
    },
    {
      "falsification": "Claim 2 differs from artifact values or receipts are missing",
      "text": "Pass 0146 records 11 source-policy captures across 6 source systems."
    },
    {
      "falsification": "Claim 3 differs from artifact values or receipts are missing",
      "text": "Pass 0146 records 12 policy rules and 10 scenario fixtures."
    },
    {
      "falsification": "Claim 4 differs from artifact values or receipts are missing",
      "text": "Pass 0146 rejects 10 negative fixtures and carries 3 prior warnings forward."
    },
    {
      "falsification": "Claim 5 differs from artifact values or receipts are missing",
      "text": "Pass 0146 promotes no theorem or natural law."
    }
  ],
  "disposition": "fenced",
  "title": "Dogfood Pass 0146 Adapter Retry Policy"
}
