{
  "ok": true,
  "thesis": {
    "id": "dc8dfef69a298991",
    "title": "Dogfood Pass 0144 One Institution Claim Graph",
    "registered_at": 1782966190.6639998,
    "disposition": "fenced",
    "seal": "dc8dfef69a298991065cc21da60e2b926fd5f040ab2f8120b4702ecfe6d79351",
    "claims": [
      {
        "id": "be2eec054a88b5e7",
        "sha256": "be2eec054a88b5e79416dde64e20aa3cf4f1e762304fe3f1cc3c653ec6ddd0f5"
      },
      {
        "id": "c3d4f1d8de0cfbab",
        "sha256": "c3d4f1d8de0cfbab6517dbab763daf0e307930220890acedab55964bbccf1cfd"
      },
      {
        "id": "e96e7862c0e6ced8",
        "sha256": "e96e7862c0e6ced885926f979921f117d60809bd4ff06c27722ba299a130e03e"
      },
      {
        "id": "e67d2b6348ffca4c",
        "sha256": "e67d2b6348ffca4c020f3c6577ead3f5c5c7a02b53230e57425380ecd1ee3fd2"
      },
      {
        "id": "8b7c0c7cac60bfe5",
        "sha256": "8b7c0c7cac60bfe5bd7c1a0e609ec2babc51caf482aea8348494404c932faf65"
      }
    ]
  },
  "refutations": [
    {
      "claim_id": "be2eec054a88b5e7",
      "claim_sha256": "be2eec054a88b5e79416dde64e20aa3cf4f1e762304fe3f1cc3c653ec6ddd0f5",
      "challenge": "test the stated falsification: Claim 1 differs from pass 0144 artifact values or receipts are missing",
      "measurable": "Claim 1 differs from pass 0144 artifact values or receipts are missing",
      "source": "null"
    },
    {
      "claim_id": "c3d4f1d8de0cfbab",
      "claim_sha256": "c3d4f1d8de0cfbab6517dbab763daf0e307930220890acedab55964bbccf1cfd",
      "challenge": "test the stated falsification: Claim 2 differs from pass 0144 artifact values or receipts are missing",
      "measurable": "Claim 2 differs from pass 0144 artifact values or receipts are missing",
      "source": "null"
    },
    {
      "claim_id": "e96e7862c0e6ced8",
      "claim_sha256": "e96e7862c0e6ced885926f979921f117d60809bd4ff06c27722ba299a130e03e",
      "challenge": "test the stated falsification: Claim 3 differs from pass 0144 artifact values or receipts are missing",
      "measurable": "Claim 3 differs from pass 0144 artifact values or receipts are missing",
      "source": "null"
    },
    {
      "claim_id": "e67d2b6348ffca4c",
      "claim_sha256": "e67d2b6348ffca4c020f3c6577ead3f5c5c7a02b53230e57425380ecd1ee3fd2",
      "challenge": "test the stated falsification: Claim 4 differs from pass 0144 artifact values or receipts are missing",
      "measurable": "Claim 4 differs from pass 0144 artifact values or receipts are missing",
      "source": "null"
    },
    {
      "claim_id": "8b7c0c7cac60bfe5",
      "claim_sha256": "8b7c0c7cac60bfe5bd7c1a0e609ec2babc51caf482aea8348494404c932faf65",
      "challenge": "test the stated falsification: Claim 5 differs from pass 0144 artifact values or receipts are missing",
      "measurable": "Claim 5 differs from pass 0144 artifact values or receipts are missing",
      "source": "null"
    }
  ],
  "assessment": {
    "started_at": 1782966190.6639998,
    "thesis_id": "dc8dfef69a298991",
    "thesis_seal": "dc8dfef69a298991065cc21da60e2b926fd5f040ab2f8120b4702ecfe6d79351",
    "claims": 5,
    "match": 5,
    "drift": 0,
    "unverifiable": 0,
    "verdict_seal": "b915a47d250e4f153c93857efb97c26e333e6f31a870a5e7d739f40dc8bd773b",
    "measurement_seal": "a60ebf438a8f6209c62656445add98f4d7538b48742e96121cd131493e23fd64",
    "disposition": "fenced",
    "stored": null,
    "verdicts": [
      {
        "claim_id": "be2eec054a88b5e7",
        "claim_sha256": "be2eec054a88b5e79416dde64e20aa3cf4f1e762304fe3f1cc3c653ec6ddd0f5",
        "status": "MATCH",
        "deviation": 0.0,
        "tolerance": 0.5,
        "margin": 1.0,
        "method": "artifact-review",
        "grounds": "deviation 0 within tolerance 0.5",
        "disposition": "fenced"
      },
      {
        "claim_id": "c3d4f1d8de0cfbab",
        "claim_sha256": "c3d4f1d8de0cfbab6517dbab763daf0e307930220890acedab55964bbccf1cfd",
        "status": "MATCH",
        "deviation": 0.0,
        "tolerance": 0.5,
        "margin": 1.0,
        "method": "artifact-review",
        "grounds": "deviation 0 within tolerance 0.5",
        "disposition": "fenced"
      },
      {
        "claim_id": "e96e7862c0e6ced8",
        "claim_sha256": "e96e7862c0e6ced885926f979921f117d60809bd4ff06c27722ba299a130e03e",
        "status": "MATCH",
        "deviation": 0.0,
        "tolerance": 0.5,
        "margin": 1.0,
        "method": "artifact-review",
        "grounds": "deviation 0 within tolerance 0.5",
        "disposition": "fenced"
      },
      {
        "claim_id": "e67d2b6348ffca4c",
        "claim_sha256": "e67d2b6348ffca4c020f3c6577ead3f5c5c7a02b53230e57425380ecd1ee3fd2",
        "status": "MATCH",
        "deviation": 0.0,
        "tolerance": 0.5,
        "margin": 1.0,
        "method": "artifact-review",
        "grounds": "deviation 0 within tolerance 0.5",
        "disposition": "fenced"
      },
      {
        "claim_id": "8b7c0c7cac60bfe5",
        "claim_sha256": "8b7c0c7cac60bfe5bd7c1a0e609ec2babc51caf482aea8348494404c932faf65",
        "status": "MATCH",
        "deviation": 0.0,
        "tolerance": 0.5,
        "margin": 1.0,
        "method": "artifact-review",
        "grounds": "deviation 0 within tolerance 0.5",
        "disposition": "fenced"
      }
    ],
    "measurements": [
      {
        "claim_id": "be2eec054a88b5e7",
        "claim_sha256": "be2eec054a88b5e79416dde64e20aa3cf4f1e762304fe3f1cc3c653ec6ddd0f5",
        "deviation": 0.0,
        "tolerance": 0.5,
        "method": "artifact-review",
        "measured_at": 1782966190.6639998,
        "evidence": [
          "schema=OneInstitutionClaimGraphReceipt/v1",
          "status=ONE_INSTITUTION_CLAIM_GRAPH_MATCH_WITH_WARNINGS",
          "seal=548a8fd61058c8dfd38765b7e9b61e2f382eacc6e759b6774f1d911efd8ac2eb"
        ]
      },
      {
        "claim_id": "c3d4f1d8de0cfbab",
        "claim_sha256": "c3d4f1d8de0cfbab6517dbab763daf0e307930220890acedab55964bbccf1cfd",
        "deviation": 0.0,
        "tolerance": 0.5,
        "method": "artifact-review",
        "measured_at": 1782966190.6639998,
        "evidence": [
          "gather_summary={'total_items': 11, 'live_captures': 6, 'protocol_docs': 5, 'distinct_bodies': 11}"
        ]
      },
      {
        "claim_id": "e96e7862c0e6ced8",
        "claim_sha256": "e96e7862c0e6ced885926f979921f117d60809bd4ff06c27722ba299a130e03e",
        "deviation": 0.0,
        "tolerance": 0.5,
        "method": "artifact-review",
        "measured_at": 1782966190.6639998,
        "evidence": [
          "join_verdicts=[{'join': 'ror_openalex_identity', 'status': 'MATCH', 'evidence': ['https://ror.org/042nb2s44', 'https://ror.org/042nb2s44', 'https://openalex.org/I63966007']}, {'join': 'dspace_oai_identify', 'status': 'MATCH', 'evidence': ['b2b32451405edb6b60fb4dcdae1448d901563f0e39d82905eb58a65c75af0768']}, {'join': 'dspace_recent_record_sample', 'status': 'MATCH', 'evidence': ['b262f6b7d3b8a97ecf99e489afc2e52fd05e3515adb773ca50b277f36c9fdadb', 'd1bea1801ff37967bd49dc1a47b45571f89ea888d02f9796194443285ad0c452']}, {'join': 'crossref_affiliation_sample', 'status': 'MATCH', 'evidence': ['26420ab6a28bc971d85278dfb1b424d05319d9671ebad8d5ba1ec5fc90cd3ba2']}, {'join': 'datacite_dataset_relation', 'status': 'SOURCE_LEAD_ONLY', 'evidence': ['61a138bafeeb506711536a18d80d892dd4ef03537395cb21a46f27c5c86b98e4', 'explicit MIT affiliation not verified in sampled records']}]"
        ]
      },
      {
        "claim_id": "e67d2b6348ffca4c",
        "claim_sha256": "e67d2b6348ffca4c020f3c6577ead3f5c5c7a02b53230e57425380ecd1ee3fd2",
        "deviation": 0.0,
        "tolerance": 0.5,
        "method": "artifact-review",
        "measured_at": 1782966190.6639998,
        "evidence": [
          "negative_fixtures=10",
          "source_warnings=3"
        ]
      },
      {
        "claim_id": "8b7c0c7cac60bfe5",
        "claim_sha256": "8b7c0c7cac60bfe5bd7c1a0e609ec2babc51caf482aea8348494404c932faf65",
        "deviation": 0.0,
        "tolerance": 0.5,
        "method": "artifact-review",
        "measured_at": 1782966190.6639998,
        "evidence": [
          "current_promoted_theorems=[]",
          "current_promoted_natural_laws=[]"
        ]
      }
    ],
    "seal": "3b42465e6698a23835dc541995cad22b42244f4839fcfcfd10dade027dd220a4"
  },
  "verdicts": [
    {
      "claim_id": "be2eec054a88b5e7",
      "claim_sha256": "be2eec054a88b5e79416dde64e20aa3cf4f1e762304fe3f1cc3c653ec6ddd0f5",
      "status": "MATCH",
      "disposition": "fenced",
      "deviation": 0.0,
      "tolerance": 0.5,
      "margin": 1.0,
      "method": "artifact-review",
      "grounds": "deviation 0 within tolerance 0.5"
    },
    {
      "claim_id": "c3d4f1d8de0cfbab",
      "claim_sha256": "c3d4f1d8de0cfbab6517dbab763daf0e307930220890acedab55964bbccf1cfd",
      "status": "MATCH",
      "disposition": "fenced",
      "deviation": 0.0,
      "tolerance": 0.5,
      "margin": 1.0,
      "method": "artifact-review",
      "grounds": "deviation 0 within tolerance 0.5"
    },
    {
      "claim_id": "e96e7862c0e6ced8",
      "claim_sha256": "e96e7862c0e6ced885926f979921f117d60809bd4ff06c27722ba299a130e03e",
      "status": "MATCH",
      "disposition": "fenced",
      "deviation": 0.0,
      "tolerance": 0.5,
      "margin": 1.0,
      "method": "artifact-review",
      "grounds": "deviation 0 within tolerance 0.5"
    },
    {
      "claim_id": "e67d2b6348ffca4c",
      "claim_sha256": "e67d2b6348ffca4c020f3c6577ead3f5c5c7a02b53230e57425380ecd1ee3fd2",
      "status": "MATCH",
      "disposition": "fenced",
      "deviation": 0.0,
      "tolerance": 0.5,
      "margin": 1.0,
      "method": "artifact-review",
      "grounds": "deviation 0 within tolerance 0.5"
    },
    {
      "claim_id": "8b7c0c7cac60bfe5",
      "claim_sha256": "8b7c0c7cac60bfe5bd7c1a0e609ec2babc51caf482aea8348494404c932faf65",
      "status": "MATCH",
      "disposition": "fenced",
      "deviation": 0.0,
      "tolerance": 0.5,
      "margin": 1.0,
      "method": "artifact-review",
      "grounds": "deviation 0 within tolerance 0.5"
    }
  ],
  "checks": {
    "seals_ok": true,
    "thesis_ok": true,
    "verdicts_rederive": true
  },
  "report": "docs\\research\\dogfood\\crucible\\pass-0144-report.md",
  "record": "docs\\research\\dogfood\\crucible\\pass-0144-run.json",
  "bundle": null,
  "spec": null,
  "review": null,
  "verifier": {
    "mode": "cleanroom",
    "inputs": [],
    "excluded": [
      "worker context",
      "reasoning trace",
      "intermediate steps"
    ],
    "checkability": "If success cannot be evaluated from the original spec and the artifact, the spec is not checkable yet."
  }
}
